env_cache.py
env_cache-0.2.dist-info/LICENSE
env_cache-0.2.dist-info/WHEEL
env_cache-0.2.dist-info/METADATA
env_cache-0.2.dist-info/RECORD
