Metadata-Version: 2.3
Name: env_cache
Version: 0.2
Summary: Get a Python environment for a Python version and requirements.txt file
Author-email: European XFEL GmbH <da-support@xfel.eu>
Classifier: License :: OSI Approved :: BSD License
Project-URL: Source, https://github.com/European-XFEL/env-cache
